mtdump/__init__.py
mtdump/_v1.py
mtdump/common.py
mtdump-0.2.0.dist-info/licenses/LICENSE
mtdump-0.2.0.dist-info/METADATA
mtdump-0.2.0.dist-info/WHEEL
mtdump-0.2.0.dist-info/top_level.txt
mtdump-0.2.0.dist-info/RECORD
