Metadata-Version: 2.4
Name: mtdump
Version: 0.2.0
Summary: A robust object serialization format with compression, encryption, checksum validation, and diagnostics metadata.
Author-email: chentl <mtdump@chen.tl>
License: MIT License
Keywords: serialization,pickle,dill,encryption,zstd,checksum,compatibility,debugging
Classifier: Programming Language :: Python :: 3
Classifier: License :: OSI Approved :: MIT License
Classifier: Operating System :: OS Independent
Classifier: Topic :: Software Development :: Libraries :: Python Modules
Classifier: Topic :: Security :: Cryptography
Requires-Python: >=3.9
License-File: LICENSE
Requires-Dist: cryptography
Requires-Dist: zstandard
Provides-Extra: dill
Requires-Dist: dill; extra == "dill"
Dynamic: license-file
